hulse/__init__.py
hulse/cli.py
hulse/client.py
hulse/errors.py
hulse/settings.py
hulse/utils.py
hulse-0.0.5.dist-info/LICENSE
hulse-0.0.5.dist-info/METADATA
hulse-0.0.5.dist-info/WHEEL
hulse-0.0.5.dist-info/entry_points.txt
hulse-0.0.5.dist-info/top_level.txt
hulse-0.0.5.dist-info/RECORD
