Metadata-Version: 2.1
Name: hulse
Version: 0.0.5
Summary: The Python client for the Hulse platform
License: MIT
License-File: LICENSE
Requires-Dist: requests
Requires-Dist: click
Requires-Dist: transformers
Requires-Dist: torch
Requires-Dist: python-dotenv
Requires-Dist: colorama
Requires-Dist: pytest
Requires-Dist: flask
Requires-Dist: appdirs
